ifc_hlm/__init__.py
ifc_hlm/models/__init__.py
ifc_hlm/models/hlm.py
ifc_hlm/models/hlm_bmi.py
ifc_hlm/models/model1.py
ifc_hlm/models/model252.py
ifc_hlm/models/model254.py
ifc_hlm/vectorized/__init__.py
ifc_hlm/vectorized/base_model.py
ifc_hlm/vectorized/bmi_model.py
ifc_hlm/vectorized/config.py
ifc_hlm/vectorized/model252.py
ifc_hlm-0.5.0.dist-info/METADATA
ifc_hlm-0.5.0.dist-info/WHEEL
ifc_hlm-0.5.0.dist-info/licenses/LICENSE
ifc_hlm-0.5.0.dist-info/RECORD
