Metadata-Version: 2.4
Name: ifc-hlm
Version: 0.5.0
Summary: Hillslope-Link Model
License-File: LICENSE
Author: Ruben Molina
Author-email: rmolina@gmail.com
Requires-Python: >=3.9
Classifier: Programming Language :: Python :: 3
Classifier: Programming Language :: Python :: 3.9
Classifier: Programming Language :: Python :: 3.10
Classifier: Programming Language :: Python :: 3.11
Classifier: Programming Language :: Python :: 3.12
Classifier: Programming Language :: Python :: 3.13
Classifier: Programming Language :: Python :: 3.14
Requires-Dist: bmipy (>=2.0)
Requires-Dist: networkx (>=2.8)
Requires-Dist: numpy (>=1.21)
Requires-Dist: pandas (>=1.4)
Requires-Dist: pyyaml (>=6.0)
Requires-Dist: scipy (>=1.9)
Requires-Dist: toml (>=0.10.2)
Requires-Dist: tqdm (>=4.60)
